mytftpy-0.8.1.data/scripts/tftpy_client.py
mytftpy-0.8.1.data/scripts/tftpy_server.py
tftpy/TftpClient.py
tftpy/TftpContexts.py
tftpy/TftpPacketFactory.py
tftpy/TftpPacketTypes.py
tftpy/TftpServer.py
tftpy/TftpShared.py
tftpy/TftpStates.py
tftpy/__init__.py
mytftpy-0.8.1.dist-info/COPYING
mytftpy-0.8.1.dist-info/METADATA
mytftpy-0.8.1.dist-info/WHEEL
mytftpy-0.8.1.dist-info/top_level.txt
mytftpy-0.8.1.dist-info/RECORD
