Metadata-Version: 2.1
Name: mytftpy
Version: 0.8.1
Summary: Python TFTP library
Home-page: https://github.com/alex-testlab/mytftpy
Author: Michael P. Soulier
Author-email: msoulier@digitaltorque.ca
Project-URL: Documentation, http://tftpy.sourceforge.net/sphinx/index.html
Project-URL: Source, https://github.com/alex-testlab/mytftpy
Project-URL: Tracker, https://github.com/alex-testlab/mytftpy
Classifier: Programming Language :: Python :: 2.7
Classifier: Programming Language :: Python :: 3
Classifier: Development Status :: 4 - Beta
Classifier: Environment :: Console
Classifier: Environment :: No Input/Output (Daemon)
Classifier: Intended Audience :: Developers
Classifier: License :: OSI Approved :: MIT License
Classifier: Operating System :: OS Independent
Classifier: Topic :: Internet
Requires-Python: >=2.7
License-File: COPYING
